pyairahome/__init__.py
pyairahome/_version.py
pyairahome/airahome.py
pyairahome/ble.py
pyairahome/cloud.py
pyairahome/commands.py
pyairahome/auth/__init__.py
pyairahome/auth/cognito_auth.py
pyairahome/auth/token_manager.py
pyairahome/config/__init__.py
pyairahome/config/settings.py
pyairahome/device/__init__.py
pyairahome/device/heat_pump/__init__.py
pyairahome/device/heat_pump/ble/__init__.py
pyairahome/device/heat_pump/ble/v1/__init__.py
pyairahome/device/heat_pump/ble/v1/chunked_message_pb2.py
pyairahome/device/heat_pump/ble/v1/chunked_message_pb2_grpc.py
pyairahome/device/heat_pump/ble/v1/get_data_pb2.py
pyairahome/device/heat_pump/ble/v1/get_data_pb2_grpc.py
pyairahome/device/heat_pump/ble/v1/main_pump_flow_pb2.py
pyairahome/device/heat_pump/ble/v1/main_pump_flow_pb2_grpc.py
pyairahome/device/heat_pump/ble/v1/system_check_state_pb2.py
pyairahome/device/heat_pump/ble/v1/system_check_state_pb2_grpc.py
pyairahome/device/heat_pump/ble/v1/wifi_network_pb2.py
pyairahome/device/heat_pump/ble/v1/wifi_network_pb2_grpc.py
pyairahome/device/heat_pump/ble/v1/wifi_networks_pb2.py
pyairahome/device/heat_pump/ble/v1/wifi_networks_pb2_grpc.py
pyairahome/device/heat_pump/cloud/__init__.py
pyairahome/device/heat_pump/cloud/v1/__init__.py
pyairahome/device/heat_pump/cloud/v1/service_pb2.py
pyairahome/device/heat_pump/cloud/v1/service_pb2_grpc.py
pyairahome/device/heat_pump/command/__init__.py
pyairahome/device/heat_pump/command/v1/__init__.py
pyairahome/device/heat_pump/command/v1/acknowledge_errors_pb2.py
pyairahome/device/heat_pump/command/v1/acknowledge_errors_pb2_grpc.py
pyairahome/device/heat_pump/command/v1/activate_hot_water_boosting_pb2.py
pyairahome/device/heat_pump/command/v1/activate_hot_water_boosting_pb2_grpc.py
pyairahome/device/heat_pump/command/v1/activate_night_mode_for_one_hour_pb2.py
pyairahome/device/heat_pump/command/v1/activate_night_mode_for_one_hour_pb2_grpc.py
pyairahome/device/heat_pump/command/v1/add_schedule_pb2.py
pyairahome-2.2.0.dist-info/licenses/LICENSE
pyairahome-2.2.0.dist-info/METADATA
pyairahome-2.2.0.dist-info/WHEEL
pyairahome-2.2.0.dist-info/top_level.txt
pyairahome-2.2.0.dist-info/RECORD
