Metadata-Version: 2.4
Name: pyairahome
Version: 2.2.0
Summary: PyAiraHome is a comprehensive Python library that provides both cloud-based and Bluetooth Low Energy (BLE) connectivity to Aira Home heat pump systems.
Author-email: "Invy55 (Marco)" <marco@invy55.win>
Maintainer-email: "Invy55 (Marco)" <marco@invy55.win>
License-Expression: Apache-2.0
Project-URL: Homepage, https://github.com/Invy55/pyairahome
Project-URL: Repository, https://github.com/Invy55/pyairahome
Project-URL: Bug Tracker, https://github.com/Invy55/pyairahome/issues
Project-URL: Documentation, https://github.com/Invy55/pyairahome#readme
Keywords: python,aira,airahome,aira home,api,wrapper,heat pump,ble,grpc
Classifier: Development Status :: 4 - Beta
Classifier: Intended Audience :: Developers
Classifier: Programming Language :: Python :: 3
Classifier: Operating System :: Unix
Classifier: Operating System :: MacOS :: MacOS X
Classifier: Operating System :: Microsoft :: Windows
Classifier: Topic :: Home Automation
Classifier: Topic :: Software Development :: Libraries :: Python Modules
Requires-Python: >=3.8
License-File: LICENSE
Requires-Dist: pycognito>=2024.5.1
Requires-Dist: grpcio>=1.72.0
Requires-Dist: protobuf>=6.31.1
Requires-Dist: bleak>=1.0.1
Requires-Dist: cryptography>=45.0.5
Requires-Dist: bleak-retry-connector>=4.4.3
Dynamic: license-file
